vschart/__init__.py
vschart/background_color.py
vschart/base.py
vschart/candlestick_series.py
vschart/chart.py
vschart/constants.py
vschart/custom_marker.py
vschart/fibonacci.py
vschart/line_series.py
vschart/marker_list.py
vschart/markers.py
vschart/rectangle.py
vschart/series_base.py
vschart/series_primitive.py
vschart/tooltip.py
vschart/trend_line.py
vschart/types.py
vschart/vertical_line.py
vschart/volume_profile.py
vschart/volume_series.py
vschart_python-1.0.7.dist-info/licenses/LICENSE
vschart_python-1.0.7.dist-info/METADATA
vschart_python-1.0.7.dist-info/WHEEL
vschart_python-1.0.7.dist-info/top_level.txt
vschart_python-1.0.7.dist-info/RECORD
