Metadata-Version: 2.4
Name: vschart-python
Version: 1.0.7
Summary: Python client for VSChart extension
Home-page: https://github.com/yourusername/vschart
Author: yiwan2
Author-email: your.email@example.com
Project-URL: Bug Tracker, https://github.com/yourusername/vschart/issues
Project-URL: Documentation, https://github.com/yourusername/vschart/tree/main/vschart-python/docs
Project-URL: Source Code, https://github.com/yourusername/vschart
Keywords: vscode,chart,trading,finance,visualization,tradingview
Classifier: Development Status :: 4 - Beta
Classifier: Intended Audience :: Developers
Classifier: Intended Audience :: Financial and Insurance Industry
Classifier: License :: OSI Approved :: MIT License
Classifier: Operating System :: OS Independent
Classifier: Programming Language :: Python :: 3
Classifier: Programming Language :: Python :: 3.7
Classifier: Programming Language :: Python :: 3.8
Classifier: Programming Language :: Python :: 3.9
Classifier: Programming Language :: Python :: 3.10
Classifier: Programming Language :: Python :: 3.11
Classifier: Topic :: Software Development :: Libraries
Classifier: Topic :: Office/Business :: Financial
Requires-Python: >=3.7
License-File: LICENSE
Requires-Dist: websocket-client>=1.6.0
Requires-Dist: numpy>=1.21.0
Requires-Dist: pandas>=1.3.0
Requires-Dist: rich>=10.0.0
Dynamic: author
Dynamic: author-email
Dynamic: classifier
Dynamic: description
Dynamic: description-content-type
Dynamic: home-page
Dynamic: keywords
Dynamic: license-file
Dynamic: project-url
Dynamic: requires-dist
Dynamic: requires-python
Dynamic: summary
